<?xml version="1.0" encoding="UTF-8"?><record_update sys_domain="global" table="sysrule_view">
    <sysrule_view action="DELETE">
        <active>true</active>
        <advanced>true</advanced>
        <condition/>
        <description/>
        <device_type>browser</device_type>
        <match_conditions>ALL</match_conditions>
        <name>Approver view</name>
        <order>100</order>
        <overrides_user_preference>true</overrides_user_preference>
        <script><![CDATA[(function overrideView(view, is_list) {

	// Add your code here
	if(gs.hasRole('x_721458_innohub_a.approver') ||gs.hasRole('x_721458_innohub_a.manager') ||gs.hasRole('admin'))
	answer = 'Approver view';  // set the new view to answer

})(view, is_list);]]></script>
        <sys_class_name>sysrule_view</sys_class_name>
        <sys_created_by>admin</sys_created_by>
        <sys_created_on>2023-12-23 18:00:03</sys_created_on>
        <sys_domain>global</sys_domain>
        <sys_domain_path>/</sys_domain_path>
        <sys_id>f6dcb4692f1f7110763ccfedf699b65a</sys_id>
        <sys_mod_count>0</sys_mod_count>
        <sys_name>Approver view</sys_name>
        <sys_overrides/>
        <sys_package display_value="InnoHub Application" source="x_721458_innohub_a">cc3e60652fdb7110763ccfedf699b67a</sys_package>
        <sys_policy/>
        <sys_scope display_value="InnoHub Application">cc3e60652fdb7110763ccfedf699b67a</sys_scope>
        <sys_update_name>sysrule_view_f6dcb4692f1f7110763ccfedf699b65a</sys_update_name>
        <sys_updated_by>admin</sys_updated_by>
        <sys_updated_on>2023-12-23 18:00:03</sys_updated_on>
        <table>x_721458_innohub_a_insightnest</table>
        <view/>
    </sysrule_view>
    <sys_update_version action="INSERT_OR_UPDATE">
        <action>DELETE</action>
        <application display_value="InnoHub Application">cc3e60652fdb7110763ccfedf699b67a</application>
        <file_path/>
        <instance_id>f09030fcdbf8b3800b9d21c405961992</instance_id>
        <instance_name>dev80260</instance_name>
        <name>sysrule_view_f6dcb4692f1f7110763ccfedf699b65a</name>
        <payload>&lt;?xml version="1.0" encoding="UTF-8"?&gt;&lt;record_update sys_domain="global" table="sysrule_view"&gt;&lt;sysrule_view action="INSERT_OR_UPDATE"&gt;&lt;active&gt;true&lt;/active&gt;&lt;advanced&gt;true&lt;/advanced&gt;&lt;condition/&gt;&lt;description/&gt;&lt;device_type&gt;browser&lt;/device_type&gt;&lt;match_conditions&gt;ALL&lt;/match_conditions&gt;&lt;name&gt;Approver view&lt;/name&gt;&lt;order&gt;100&lt;/order&gt;&lt;overrides_user_preference&gt;true&lt;/overrides_user_preference&gt;&lt;script&gt;&lt;![CDATA[(function overrideView(view, is_list) {

	// Add your code here
	if(gs.hasRole('x_721458_innohub_a.approver') ||gs.hasRole('x_721458_innohub_a.manager') ||gs.hasRole('admin'))
	answer = 'Approver view';  // set the new view to answer

})(view, is_list);]]&gt;&lt;/script&gt;&lt;sys_class_name&gt;sysrule_view&lt;/sys_class_name&gt;&lt;sys_created_by&gt;admin&lt;/sys_created_by&gt;&lt;sys_created_on&gt;2023-12-23 18:00:03&lt;/sys_created_on&gt;&lt;sys_domain&gt;global&lt;/sys_domain&gt;&lt;sys_domain_path&gt;/&lt;/sys_domain_path&gt;&lt;sys_id&gt;f6dcb4692f1f7110763ccfedf699b65a&lt;/sys_id&gt;&lt;sys_mod_count&gt;0&lt;/sys_mod_count&gt;&lt;sys_name&gt;Approver view&lt;/sys_name&gt;&lt;sys_overrides/&gt;&lt;sys_package display_value="InnoHub Application" source="x_721458_innohub_a"&gt;cc3e60652fdb7110763ccfedf699b67a&lt;/sys_package&gt;&lt;sys_policy/&gt;&lt;sys_scope display_value="InnoHub Application"&gt;cc3e60652fdb7110763ccfedf699b67a&lt;/sys_scope&gt;&lt;sys_update_name&gt;sysrule_view_f6dcb4692f1f7110763ccfedf699b65a&lt;/sys_update_name&gt;&lt;sys_updated_by&gt;admin&lt;/sys_updated_by&gt;&lt;sys_updated_on&gt;2023-12-23 18:00:03&lt;/sys_updated_on&gt;&lt;table&gt;x_721458_innohub_a_insightnest&lt;/table&gt;&lt;view/&gt;&lt;/sysrule_view&gt;&lt;/record_update&gt;</payload>
        <payload_hash>347719774</payload_hash>
        <record_name>Approver view</record_name>
        <reverted_from/>
        <source>11c030692fdb7110763ccfedf699b636</source>
        <source_table>sys_update_set</source_table>
        <state>previous</state>
        <sys_created_by>admin</sys_created_by>
        <sys_created_on>2023-12-23 18:00:03</sys_created_on>
        <sys_id>8e7d30692f1f7110763ccfedf699b659</sys_id>
        <sys_mod_count>0</sys_mod_count>
        <sys_recorded_at>18c97d589ef0000001</sys_recorded_at>
        <sys_updated_by>admin</sys_updated_by>
        <sys_updated_on>2023-12-23 18:00:03</sys_updated_on>
        <type>View Rule</type>
        <update_guid>c27d3069951f711091e6f386f2928e59</update_guid>
        <update_guid_history>c27d3069951f711091e6f386f2928e59:347719774</update_guid_history>
    </sys_update_version>
    <sys_metadata_delete action="INSERT_OR_UPDATE">
        <sys_audit_delete/>
        <sys_class_name>sys_metadata_delete</sys_class_name>
        <sys_created_by>admin</sys_created_by>
        <sys_created_on>2023-12-23 18:03:02</sys_created_on>
        <sys_db_object display_value="" name="sysrule_view">sysrule_view</sys_db_object>
        <sys_id>13f1dea3f34449dcbbda964dc0f02e44</sys_id>
        <sys_metadata>f6dcb4692f1f7110763ccfedf699b65a</sys_metadata>
        <sys_mod_count>0</sys_mod_count>
        <sys_name>Approver view</sys_name>
        <sys_package display_value="InnoHub Application" source="x_721458_innohub_a">cc3e60652fdb7110763ccfedf699b67a</sys_package>
        <sys_parent display_value="InsightNest">c63074292fdb7110763ccfedf699b658</sys_parent>
        <sys_policy/>
        <sys_scope display_value="InnoHub Application">cc3e60652fdb7110763ccfedf699b67a</sys_scope>
        <sys_scope_delete display_value="">bdeeee2d2038447c91517686cd56cc10</sys_scope_delete>
        <sys_update_name>sysrule_view_f6dcb4692f1f7110763ccfedf699b65a</sys_update_name>
        <sys_update_version display_value="sysrule_view_f6dcb4692f1f7110763ccfedf699b65a">8e7d30692f1f7110763ccfedf699b659</sys_update_version>
        <sys_updated_by>admin</sys_updated_by>
        <sys_updated_on>2023-12-23 18:03:02</sys_updated_on>
    </sys_metadata_delete>
</record_update>
